discord_webhooks.py
Discord_Webhooks-1.0.3.dist-info/METADATA
Discord_Webhooks-1.0.3.dist-info/RECORD
Discord_Webhooks-1.0.3.dist-info/WHEEL
Discord_Webhooks-1.0.3.dist-info/top_level.txt
