Metadata-Version: 2.1
Name: Discord-Webhooks
Version: 1.0.3
Summary: Easy to use package for Python which allows for sending of webhooks to a Discord server.
Home-page: https://github.com/JamesIves/discord-webhooks
Author: James Ives
Author-email: iam@jamesiv.es
License: MIT
Platform: UNKNOWN
Classifier: Development Status :: 5 - Production/Stable
Classifier: Environment :: Other Environment
Classifier: Intended Audience :: Developers
Classifier: License :: OSI Approved :: MIT License
Classifier: Programming Language :: Python :: 3
Classifier: Programming Language :: Python :: 3.6
Requires-Dist: requests (==2.20.0)
